{"Shots on Goal":{"home":"6","away":"3"},"Shots off Goal":{"home":"8","away":"3"},"Total Shots":{"home":"19","away":"6"},"Blocked Shots":{"home":"5","away":"0"},"Shots insidebox":{"home":"14","away":"6"},"Shots outsidebox":{"home":"5","away":"0"},"Fouls":{"home":"10","away":"9"},"Corner Kicks":{"home":"4","away":"0"},"Offsides":{"home":"3","away":"0"},"Ball Possession":{"home":"56%","away":"44%"},"Yellow Cards":{"home":"1","away":"1"},"Red Cards":{"home":null,"away":null},"Goalkeeper Saves":{"home":"2","away":"4"},"Total passes":{"home":"611","away":"478"},"Passes accurate":{"home":"540","away":"383"},"Passes %":{"home":"88%","away":"80%"},"expected_goals":{"home":"2.95","away":"0.83"}}