{"Shots on Goal":{"home":"2","away":"5"},"Shots off Goal":{"home":"8","away":"5"},"Total Shots":{"home":"18","away":"12"},"Blocked Shots":{"home":"8","away":"2"},"Shots insidebox":{"home":"9","away":"6"},"Shots outsidebox":{"home":"9","away":"6"},"Fouls":{"home":"9","away":"15"},"Corner Kicks":{"home":"9","away":"4"},"Offsides":{"home":"1","away":"2"},"Ball Possession":{"home":"45%","away":"55%"},"Yellow Cards":{"home":"6","away":"2"},"Red Cards":{"home":null,"away":null},"Goalkeeper Saves":{"home":"4","away":"2"},"Total passes":{"home":"360","away":"450"},"Passes accurate":{"home":"259","away":"355"},"Passes %":{"home":"72%","away":"79%"},"expected_goals":{"home":"1.00","away":"0.70"}}