{"Shots on Goal":{"home":"7","away":"5"},"Shots off Goal":{"home":"4","away":"6"},"Total Shots":{"home":"20","away":"15"},"Blocked Shots":{"home":"9","away":"4"},"Shots insidebox":{"home":"15","away":"13"},"Shots outsidebox":{"home":"5","away":"2"},"Fouls":{"home":"9","away":"10"},"Corner Kicks":{"home":"4","away":"5"},"Offsides":{"home":"3","away":"0"},"Ball Possession":{"home":"59%","away":"41%"},"Yellow Cards":{"home":null,"away":null},"Red Cards":{"home":null,"away":null},"Goalkeeper Saves":{"home":"3","away":"3"},"Total passes":{"home":"553","away":"391"},"Passes accurate":{"home":"477","away":"321"},"Passes %":{"home":"86%","away":"82%"},"expected_goals":{"home":"2.82","away":"1.45"}}