{"Shots on Goal":{"home":"3","away":"4"},"Shots off Goal":{"home":"3","away":"8"},"Total Shots":{"home":"8","away":"18"},"Blocked Shots":{"home":"2","away":"6"},"Shots insidebox":{"home":"6","away":"13"},"Shots outsidebox":{"home":"2","away":"5"},"Fouls":{"home":"19","away":"9"},"Corner Kicks":{"home":"2","away":"10"},"Offsides":{"home":"3","away":"1"},"Ball Possession":{"home":"46%","away":"54%"},"Yellow Cards":{"home":"5","away":"2"},"Red Cards":{"home":"1","away":"0"},"Goalkeeper Saves":{"home":"3","away":"2"},"Total passes":{"home":"358","away":"395"},"Passes accurate":{"home":"283","away":"330"},"Passes %":{"home":"79%","away":"84%"},"expected_goals":{"home":"1.68","away":"1.61"}}