{"Shots on Goal":{"home":"7","away":"4"},"Shots off Goal":{"home":"8","away":"4"},"Total Shots":{"home":"22","away":"11"},"Blocked Shots":{"home":"7","away":"3"},"Shots insidebox":{"home":"14","away":"9"},"Shots outsidebox":{"home":"8","away":"2"},"Fouls":{"home":"12","away":"13"},"Corner Kicks":{"home":"7","away":"4"},"Offsides":{"home":"2","away":"1"},"Ball Possession":{"home":"64%","away":"36%"},"Yellow Cards":{"home":"0","away":"2"},"Red Cards":{"home":null,"away":null},"Goalkeeper Saves":{"home":"3","away":"4"},"Total passes":{"home":"636","away":"345"},"Passes accurate":{"home":"563","away":"271"},"Passes %":{"home":"89%","away":"79%"},"expected_goals":{"home":"3.06","away":"1.11"}}