{"Shots on Goal":{"home":"5","away":"2"},"Shots off Goal":{"home":"8","away":"3"},"Total Shots":{"home":"15","away":"11"},"Blocked Shots":{"home":"2","away":"6"},"Shots insidebox":{"home":"9","away":"6"},"Shots outsidebox":{"home":"6","away":"5"},"Fouls":{"home":"13","away":"4"},"Corner Kicks":{"home":"7","away":"6"},"Offsides":{"home":"0","away":"2"},"Ball Possession":{"home":"45%","away":"55%"},"Yellow Cards":{"home":"0","away":"2"},"Red Cards":{"home":"0","away":"1"},"Goalkeeper Saves":{"home":"2","away":"3"},"Total passes":{"home":"446","away":"551"},"Passes accurate":{"home":"377","away":"499"},"Passes %":{"home":"85%","away":"91%"}}