{"Shots on Goal":{"home":"8","away":"2"},"Shots off Goal":{"home":"4","away":"4"},"Total Shots":{"home":"15","away":"9"},"Blocked Shots":{"home":"3","away":"3"},"Shots insidebox":{"home":"9","away":"6"},"Shots outsidebox":{"home":"6","away":"3"},"Fouls":{"home":"8","away":"14"},"Corner Kicks":{"home":"10","away":"3"},"Offsides":{"home":"2","away":"1"},"Ball Possession":{"home":"58%","away":"42%"},"Yellow Cards":{"home":"3","away":"3"},"Red Cards":{"home":null,"away":null},"Goalkeeper Saves":{"home":"2","away":"7"},"Total passes":{"home":"494","away":"356"},"Passes accurate":{"home":"431","away":"291"},"Passes %":{"home":"87%","away":"82%"}}