{"Shots on Goal":{"home":"6","away":"3"},"Shots off Goal":{"home":"3","away":"2"},"Total Shots":{"home":"10","away":"10"},"Blocked Shots":{"home":"1","away":"5"},"Shots insidebox":{"home":"8","away":"7"},"Shots outsidebox":{"home":"2","away":"3"},"Fouls":{"home":"8","away":"7"},"Corner Kicks":{"home":"4","away":"5"},"Offsides":{"home":"0","away":"2"},"Ball Possession":{"home":"44%","away":"56%"},"Yellow Cards":{"home":"2","away":"1"},"Red Cards":{"home":null,"away":null},"Goalkeeper Saves":{"home":"1","away":"3"},"Total passes":{"home":"459","away":"584"},"Passes accurate":{"home":"391","away":"520"},"Passes %":{"home":"85%","away":"89%"}}