{"Shots on Goal":{"home":"8","away":"2"},"Shots off Goal":{"home":"6","away":"5"},"Total Shots":{"home":"18","away":"10"},"Blocked Shots":{"home":"4","away":"3"},"Shots insidebox":{"home":"14","away":"6"},"Shots outsidebox":{"home":"4","away":"4"},"Fouls":{"home":"11","away":"6"},"Corner Kicks":{"home":"10","away":"2"},"Offsides":{"home":"2","away":"0"},"Ball Possession":{"home":"58%","away":"42%"},"Yellow Cards":{"home":"3","away":"0"},"Red Cards":{"home":null,"away":null},"Goalkeeper Saves":{"home":"1","away":"5"},"Total passes":{"home":"554","away":"410"},"Passes accurate":{"home":"471","away":"337"},"Passes %":{"home":"85%","away":"82%"}}