{"Shots on Goal":{"home":"6","away":"5"},"Shots off Goal":{"home":"4","away":"8"},"Total Shots":{"home":"13","away":"19"},"Blocked Shots":{"home":"3","away":"6"},"Shots insidebox":{"home":"10","away":"10"},"Shots outsidebox":{"home":"3","away":"9"},"Fouls":{"home":"10","away":"11"},"Corner Kicks":{"home":"6","away":"7"},"Offsides":{"home":"3","away":"2"},"Ball Possession":{"home":"43%","away":"57%"},"Yellow Cards":{"home":"4","away":"1"},"Red Cards":{"home":null,"away":null},"Goalkeeper Saves":{"home":"4","away":"5"},"Total passes":{"home":"288","away":"381"},"Passes accurate":{"home":"190","away":"284"},"Passes %":{"home":"66%","away":"75%"}}