{"Shots on Goal":{"home":"6","away":"8"},"Shots off Goal":{"home":"9","away":"1"},"Total Shots":{"home":"29","away":"10"},"Blocked Shots":{"home":"14","away":"1"},"Shots insidebox":{"home":"17","away":"8"},"Shots outsidebox":{"home":"12","away":"2"},"Fouls":{"home":"9","away":"7"},"Corner Kicks":{"home":"10","away":"2"},"Offsides":{"home":"2","away":"2"},"Ball Possession":{"home":"75%","away":"25%"},"Yellow Cards":{"home":"2","away":"2"},"Red Cards":{"home":null,"away":null},"Goalkeeper Saves":{"home":"5","away":"5"},"Total passes":{"home":"622","away":"216"},"Passes accurate":{"home":"530","away":"123"},"Passes %":{"home":"85%","away":"57%"}}